spsdk_lauterbach/__init__.py
spsdk_lauterbach/probe.py
spsdk_lauterbach/__pyinstaller/__init__.py
spsdk_lauterbach/__pyinstaller/hook-spsdk_lauterbach.py
spsdk_lauterbach-0.3.0.dist-info/LICENSE
spsdk_lauterbach-0.3.0.dist-info/METADATA
spsdk_lauterbach-0.3.0.dist-info/WHEEL
spsdk_lauterbach-0.3.0.dist-info/entry_points.txt
spsdk_lauterbach-0.3.0.dist-info/top_level.txt
spsdk_lauterbach-0.3.0.dist-info/RECORD
